{
  "arr-l.png": "arr-l-14d75722f5.png",
  "arr-r.png": "arr-r-5754bec84e.png",
  "bg1.png": "bg1-faf91b8890.png",
  "bg2.png": "bg2-76432ec735.png",
  "bg3.png": "bg3-2d972c4a8e.png",
  "first.png": "first-fe3311e545.png",
  "first/first-1.png": "first/first-1-2bf337a77c.png",
  "first/first-2.png": "first/first-2-9f4f0bd042.png",
  "first/first-3.png": "first/first-3-9cd8296091.png",
  "first/first.png": "first/first-144d0e187c.png",
  "first/first4.png": "first/first4-e9cc72bdad.png",
  "line-1.png": "line-1-c7949dbd95.png",
  "line.png": "line-16de494fba.png",
  "n1.png": "n1-d7b2655d76.png",
  "n2.png": "n2-5cfa13b79e.png",
  "n3.png": "n3-20031ef08a.png",
  "n4.png": "n4-42e06a19b8.png",
  "n5.png": "n5-e1d88e3893.png",
  "n6.png": "n6-c2105b86d0.png",
  "n7.png": "n7-12abb4631e.png",
  "n8.png": "n8-9546221e9c.png",
  "p1-1.png": "p1-1-2140757bd1.png",
  "p1.png": "p1-7cbb583164.png",
  "s1/book-icon.png": "s1/book-icon-65600d3a67.png",
  "s1/money-icon-1.png": "s1/money-icon-1-7de549f7fd.png",
  "s1/money-icon-2.png": "s1/money-icon-2-e858bd887b.png",
  "s1/people-ion.png": "s1/people-ion-6e55463c49.png",
  "s1/title-1.png": "s1/title-1-64157fe882.png",
  "s2/images/page6-1-echarts.png": "s2/images/page6-1-echarts-d8d5bcbd7f.png",
  "s2/images/page6-2-echarts.png": "s2/images/page6-2-echarts-49ec6c5972.png",
  "s2/images/page6-3-echarts.png": "s2/images/page6-3-echarts-c4ca35ac0e.png",
  "s2/images/page6-4-echarts.png": "s2/images/page6-4-echarts-f66aa3805c.png",
  "s2/images/page6-5-echarts.png": "s2/images/page6-5-echarts-3a21fcd5fc.png",
  "s2/images/profit.png": "s2/images/profit-e22575f8e7.png",
  "s2/p2-p2-p4.png": "s2/p2-p2-p4-cf6a87d1fd.png",
  "s2/p2-p4-p1-1.png": "s2/p2-p4-p1-1-f499fe58ba.png",
  "s2/p2-p4-p1-2.png": "s2/p2-p4-p1-2-29bc95f2ef.png",
  "s2/p2-p4-p1-3.png": "s2/p2-p4-p1-3-ad5474a798.png",
  "s2/p2-p4-p1.png": "s2/p2-p4-p1-abd090bb70.png",
  "s2/p2-p4-p2.png": "s2/p2-p4-p2-047ab5391e.png",
  "s2/p2-p4-p20000.png": "s2/p2-p4-p20000-b1de25a53e.png",
  "s2/p2-p7-p1.png": "s2/p2-p7-p1-07c179ef66.png",
  "s2/p2-p7-p2.png": "s2/p2-p7-p2-ac468e0de4.png",
  "s2/p2-p8-p1.png": "s2/p2-p8-p1-1ece6d524a.png",
  "s2/page6-1-echarts.png": "s2/page6-1-echarts-d4abe03200.png",
  "s2/page6-2-echarts.png": "s2/page6-2-echarts-dfe2d014af.png",
  "s2/page6-3-echarts.png": "s2/page6-3-echarts-41c8a12a23.png",
  "s2/page6-4-echarts.png": "s2/page6-4-echarts-1a55bd0f22.png",
  "s2/page6-5-echarts.png": "s2/page6-5-echarts-303888639d.png",
  "s2/profit.png": "s2/profit-e22575f8e7.png",
  "s2/s2-p1-1.png": "s2/s2-p1-1-79f8d36ff9.png",
  "s2/s2-p1-p1.png": "s2/s2-p1-p1-a7ebf3896f.png",
  "s2/s2-p1-p2.png": "s2/s2-p1-p2-816dcd82cb.png",
  "s2/s2-p1-p3.png": "s2/s2-p1-p3-53b257eea2.png",
  "s2/s2-p2-1.png": "s2/s2-p2-1-b3cf9979bb.png",
  "s2/s2-p2-p1.png": "s2/s2-p2-p1-bf9b69a4f1.png",
  "s2/s2-p2-p2.png": "s2/s2-p2-p2-ee8ef6833e.png",
  "s2/s2-p2-p3.png": "s2/s2-p2-p3-3bf3b1dfb7.png",
  "s2/s2-p3-p1.png": "s2/s2-p3-p1-8cef5f3e85.png",
  "s2/s2-p3-p2.png": "s2/s2-p3-p2-2eeedcdc1e.png",
  "s2/s2-p3-p3.png": "s2/s2-p3-p3-a2e96d98d4.png",
  "s2/s3-title.png": "s2/s3-title-9c9cffa633.png",
  "s2/tips.png": "s2/tips-33c5ce2a36.png",
  "s2/title-2.png": "s2/title-2-4e5e75742f.png",
  "s3/s3-p1.png": "s3/s3-p1-835ae8d8b1.png",
  "s3/s3-title.png": "s3/s3-title-bdf1e03aeb.png",
  "s4/s4-app-p1.png": "s4/s4-app-p1-c47bd41ff8.png",
  "s4/s4-app-p2.png": "s4/s4-app-p2-9df409e2fa.png",
  "s4/s4-app-p3.png": "s4/s4-app-p3-a0b2efc040.png",
  "s4/s4-app-p4.png": "s4/s4-app-p4-3951552b10.png",
  "s4/s4-pc-p1.png": "s4/s4-pc-p1-a9f854d71a.png",
  "s4/s4-pc-p2.png": "s4/s4-pc-p2-e4a1c8ed63.png",
  "s4/s4-pc-p3.png": "s4/s4-pc-p3-0655e182e0.png",
  "s4/s4-pc-p4.png": "s4/s4-pc-p4-97e415ab07.png",
  "s4/s4-title.png": "s4/s4-title-b72a22b19d.png",
  "s5/s5-p1.png": "s5/s5-p1-3d06f32d5b.png",
  "s5/s5-p10.png": "s5/s5-p10-f2860e1a8d.png",
  "s5/s5-p11.png": "s5/s5-p11-3f4258ad0d.png",
  "s5/s5-p12.png": "s5/s5-p12-901626ffa9.png",
  "s5/s5-p2.png": "s5/s5-p2-d6cb847618.png",
  "s5/s5-p3.png": "s5/s5-p3-e0e69f42c6.png",
  "s5/s5-p4.png": "s5/s5-p4-cfecb460a4.png",
  "s5/s5-p5.png": "s5/s5-p5-a9f977a847.png",
  "s5/s5-p6.png": "s5/s5-p6-1182518124.png",
  "s5/s5-p7.png": "s5/s5-p7-f1d0d6793b.png",
  "s5/s5-p8.png": "s5/s5-p8-45b6c78832.png",
  "s5/s5-p9.png": "s5/s5-p9-de57c65731.png",
  "s5/s5-title.png": "s5/s5-title-db6235a635.png",
  "s6/s6-p1-1.png": "s6/s6-p1-1-6656627dae.png",
  "s6/s6-p1-2.png": "s6/s6-p1-2-c9bb0aa79a.png",
  "s6/s6-p1-3.png": "s6/s6-p1-3-c07fdf0658.png",
  "s6/s6-p1.png": "s6/s6-p1-f0a7e4c820.png",
  "s6/s6-title.png": "s6/s6-title-2f0cda8229.png",
  "s7/s7-p1-1.png": "s7/s7-p1-1-84be2a6975.png",
  "s7/s7-p1-2.png": "s7/s7-p1-2-574d40aa84.png",
  "s7/s7-p1-3.png": "s7/s7-p1-3-29d5560cc0.png",
  "s7/s7-title.png": "s7/s7-title-82e84edb22.png",
  "s8/end-logo.png": "s8/end-logo-2c754b289a.png",
  "s8/end-p2.png": "s8/end-p2-c2561db1cc.png",
  "s8/ew-1.png": "s8/ew-1-d7621beb1b.png",
  "s8/ew-2.png": "s8/ew-2-5baec74e94.png",
  "s8/ew-3.png": "s8/ew-3-e924971426.png",
  "s8/s8-p1.png": "s8/s8-p1-350a3c8b77.png",
  "s8/s8-p2.png": "s8/s8-p2-3964706397.png",
  "s8/s8-title.png": "s8/s8-title-700656a2d4.png",
  "share.png": "share-123a250aa2.png"
}